{
  "_book/gitbook/gitbook-plugin-fontsettings/website.css": "_book/gitbook/gitbook-plugin-fontsettings/website.css?v=056a6db3ee",
  "_book/gitbook/gitbook-plugin-highlight/ebook.css": "_book/gitbook/gitbook-plugin-highlight/ebook.css?v=fa203ae16a",
  "_book/gitbook/gitbook-plugin-highlight/website.css": "_book/gitbook/gitbook-plugin-highlight/website.css?v=acce01e3e1",
  "_book/gitbook/gitbook-plugin-search/search.css": "_book/gitbook/gitbook-plugin-search/search.css?v=6c8330e8aa",
  "_book/gitbook/style.css": "_book/gitbook/style.css?v=404e82e126",
  "css/common.css": "css/common.css?v=17dfa4b13a",
  "css/common/font/iconfont.css": "css/common/font/iconfont.css?v=2f744d0535",
  "css/pages/book/catalog.css": "css/pages/book/catalog.css?v=12f3fb80fd",
  "css/pages/book/catalogInfo.css": "css/pages/book/catalogInfo.css?v=2004de8bcc",
  "css/pages/book/index.css": "css/pages/book/index.css?v=47fd7c978b",
  "css/pages/book/info.css": "css/pages/book/info.css?v=8ea7e0a1cb",
  "css/pages/book/search.css": "css/pages/book/search.css?v=d633f70329",
  "css/pages/home/index.css": "css/pages/home/index.css?v=50464b11dc",
  "lib/swiper/dist/css/swiper.css": "lib/swiper/dist/css/swiper.css?v=1851f33dc9",
  "lib/swiper/dist/css/swiper.min.css": "lib/swiper/dist/css/swiper.min.css?v=9aade19d0a"
}